cognitopy/__init__.py
cognitopy/cognitopy.py
cognitopy/enums.py
cognitopy/exceptions.py
cognitopy/schemas.py
cognitopy-1.1.6.dist-info/LICENSE
cognitopy-1.1.6.dist-info/METADATA
cognitopy-1.1.6.dist-info/WHEEL
cognitopy-1.1.6.dist-info/RECORD
