Metadata-Version: 2.1
Name: cognitopy
Version: 1.1.6
Summary: Python package to use aws cognito in a simple way
Home-page: https://github.com/DaniMG95/cognitopy
Author: Daniel Muñoz Gonzalez
Author-email: dani16595@gmail.com
Requires-Python: >=3.10.0,<4.0.0
Classifier: Programming Language :: Python :: 3
Classifier: Programming Language :: Python :: 3.10
Classifier: Programming Language :: Python :: 3.11
Classifier: Programming Language :: Python :: 3.12
Classifier: Programming Language :: Python :: 3.13
Requires-Dist: boto3 (>=1.34.117,<2.0.0)
Requires-Dist: pydantic (>=2.7.2,<3.0.0)
Requires-Dist: python-jose (>=3.3.0,<4.0.0)
Project-URL: Documentation, https://github.com/DaniMG95/cognitopy/blob/main/README.md
Project-URL: Repository, https://github.com/DaniMG95/cognitopy
